wzftest/action.json
wzftest/block.py
wzftest/demo.sh
wzftest/main.py
wzftest/planning_time.json
wzftest/readme.md
wzftest/task.py
wzftest/test.py
wzftest/tools.py
wzftest/transform.py
wzftest/.idea/RobotPackingBenchmark-main.iml
wzftest/.idea/misc.xml
wzftest/.idea/modules.xml
wzftest/.idea/workspace.xml
wzftest/.idea/inspectionProfiles/Project_Default.xml
wzftest/.idea/inspectionProfiles/profiles_settings.xml
wzftest/__pycache__/block.cpython-37.pyc
wzftest/__pycache__/block.cpython-39.pyc
wzftest/__pycache__/task.cpython-37.pyc
wzftest/__pycache__/task.cpython-39.pyc
wzftest/__pycache__/tools.cpython-37.pyc
wzftest/__pycache__/transform.cpython-37.pyc
wzftest/__pycache__/transform.cpython-39.pyc
wzftest/arm_pybullet_env/debug_abb_robot.py
wzftest/arm_pybullet_env/arm_envs/__init__.py
wzftest/arm_pybullet_env/arm_envs/arm.py
wzftest/arm_pybullet_env/arm_envs/cameras.py
wzftest/arm_pybullet_env/arm_envs/debug.py
wzftest/arm_pybullet_env/arm_envs/envs.py
wzftest/arm_pybullet_env/arm_envs/grippers.py
wzftest/arm_pybullet_env/arm_envs/moma.py
wzftest/arm_pybullet_env/arm_envs/pb_ompl.py
wzftest/arm_pybullet_env/arm_envs/task.py
wzftest/arm_pybullet_env/arm_envs/__pycache__/__init__.cpython-37.pyc
wzftest/arm_pybullet_env/arm_envs/__pycache__/arm.cpython-37.pyc
wzftest/arm_pybullet_env/arm_envs/__pycache__/cameras.cpython-37.pyc
wzftest/arm_pybullet_env/arm_envs/__pycache__/envs.cpython-37.pyc
wzftest/arm_pybullet_env/arm_envs/__pycache__/grippers.cpython-37.pyc
wzftest/arm_pybullet_env/arm_envs/__pycache__/irb2400.cpython-37.pyc
wzftest/arm_pybullet_env/arm_envs/__pycache__/irb6640.cpython-37.pyc
wzftest/arm_pybullet_env/arm_envs/__pycache__/pb_ompl.cpython-37.pyc
wzftest/arm_pybullet_env/arm_envs/__pycache__/task.cpython-37.pyc
wzftest/arm_pybullet_env/arm_envs/__pycache__/ur5.cpython-37.pyc
wzftest/arm_pybullet_env/arm_envs/models/__init__.py
wzftest/arm_pybullet_env/arm_envs/models/__pycache__/__init__.cpython-37.pyc
wzftest-0.0.1.dist-info/LICENSE
wzftest-0.0.1.dist-info/METADATA
wzftest-0.0.1.dist-info/WHEEL
wzftest-0.0.1.dist-info/top_level.txt
wzftest-0.0.1.dist-info/RECORD
